.gitignore
.travis.yml
LICENSE
MANIFEST.in
Makefile
README.md
VERSION
requirements.txt
setup.py
test-requirements.txt
migrations/alembic.ini
migrations/env.py
migrations/script.py.mako
migrations/versions/29bf27973b9e_.py
migrations/versions/5ab1880bc47f_.py
migrations/versions/6686c9ff83_.py
migrations/versions/a20f1b94160_.py
newslynx/__init__.py
newslynx/client.py
newslynx/constants.py
newslynx/core.py
newslynx/defaults.py
newslynx/exc.py
newslynx/init.py
newslynx/logs.py
newslynx/merlynne.py
newslynx/notify.py
newslynx/scheduler.py
newslynx/settings.py
newslynx/util.py
newslynx.egg-info/PKG-INFO
newslynx.egg-info/SOURCES.txt
newslynx.egg-info/dependency_links.txt
newslynx.egg-info/entry_points.txt
newslynx.egg-info/namespace_packages.txt
newslynx.egg-info/not-zip-safe
newslynx.egg-info/requires.txt
newslynx.egg-info/top_level.txt
newslynx/app/config.yaml
newslynx/app/sous-chefs.txt
newslynx/app/defaults/recipes.yaml
newslynx/app/defaults/tags.yaml
newslynx/cli/__init__.py
newslynx/cli/api.py
newslynx/cli/common.py
newslynx/cli/cron.py
newslynx/cli/db.py
newslynx/cli/debug.py
newslynx/cli/dev.py
newslynx/cli/echo.py
newslynx/cli/init.py
newslynx/cli/sc_create.py
newslynx/cli/sc_docs.py
newslynx/cli/sc_install.py
newslynx/cli/sc_run.py
newslynx/cli/sc_sync.py
newslynx/cli/version.py
newslynx/dev/__init__.py
newslynx/dev/random_data.py
newslynx/dev/fixtures/thumbnail.txt
newslynx/lib/__init__.py
newslynx/lib/article.py
newslynx/lib/author.py
newslynx/lib/common.py
newslynx/lib/dates.py
newslynx/lib/doc.py
newslynx/lib/embed.py
newslynx/lib/html.py
newslynx/lib/image.py
newslynx/lib/mail.py
newslynx/lib/meta.py
newslynx/lib/network.py
newslynx/lib/regex.py
newslynx/lib/search.py
newslynx/lib/serialize.py
newslynx/lib/stats.py
newslynx/lib/text.py
newslynx/lib/url.py
newslynx/lib/pkg/__init__.py
newslynx/lib/pkg/crontab.py
newslynx/lib/pkg/pandoc.py
newslynx/lib/pkg/validate_email.py
newslynx/models/__init__.py
newslynx/models/auth.py
newslynx/models/author.py
newslynx/models/cache.py
newslynx/models/compare_cache.py
newslynx/models/computed_metric_schema.py
newslynx/models/content_item.py
newslynx/models/content_metric.py
newslynx/models/event.py
newslynx/models/extract_cache.py
newslynx/models/metric.py
