Metadata-Version: 1.1
Name: newslynx
Version: 1.2.1
Summary: A modular toolkit for analytics.
Home-page: http://newslynx.org
Author: Brian Abelson
Author-email: brian@newslynx.org
License: CCSA-4.0
Keywords: journalism analytics google-analytics twitter facebook metrics
Platform: UNKNOWN
Classifier: Development Status :: 3 - Alpha
Classifier: Intended Audience :: Developers
Classifier: Operating System :: OS Independent
Classifier: Programming Language :: Python
